{"title": "6P + VUE + BALCON PLEIN CIEL + 2 PARKING + CAVE", "price": "\u20ac1\u00a0440\u00a0000", "body": "\n\nQR Code Link to This Post\n\n\n75012 Au c\u0153ur des Commerces, au pied du M\u00e9tro Michel Bizot, du March\u00e9, des \u00c9coles et du Bois, Immeuble R\u00e9cent raval\u00e9 tr\u00e8s s\u00e9curis\u00e9, tr\u00e8s Bien entretenu avec gardien, 10\u00e8me et DERNIER \u00e9tage avec ascenseur, 6 Pi\u00e8ces familial distribu\u00e9 en \u00c9toile, long\u00e9 d\u2019un Balcon PLEIN CIEL et Dominant Paris offrant une vue \u00e9poustouflante d\u2019\u00e9merveillement, compos\u00e9: entr\u00e9e, Triple s\u00e9jour avec double orientation, une grande cuisine d\u00eenatoire, 3 chambres (possibilit\u00e9 4) dont une suite parentale avec sa salle de bains (avec water-closet) et son dressing privatifs, une salle de bains ind\u00e9pendante avec water-closet), nombreux placards Au sous-sol + CAVE + 2 PARKING 60 Lots/7600/an (Chauffage, eau froide et chaude, gardien\u2026)- Travaux \u00e0 Pr\u00e9voir - TR\u00c8S GROS POTENTIEL \u2013 NICHE DANS LE CIEL SANS AUCUN VIS-A-VIS \n\n75012 At the heart of the shops, at the foot of the Metro Michel Bizot, the Market, Schools and Wood, Recently renovated building very secure, very Well maintained with caretaker, 10th and LAST floor with elevator, 6 Family rooms distributed in Star, along a Balcony PLEIN CIEL and Dominant Paris offering a breathtaking view of wonder, composed of: entrance, Triple living room with double orientation, a large dining kitchen, 3 bedrooms (possibility 4) including a master suite with its bathroom (with water-closet) and its private dressing room, an independent bathroom with water-closet), many closets In the basement + CELLAR + 2 PARKING 60 Lots/7600/year (Heating, cold and hot water, caretaker\u2026 )- Work to be planned - VERY LARGE POTENTIAL - NICHE IN THE SKY WITH NO VIS-A-VIS    ", "post_id": "7377828738", "created_time": "2021-09-09T16:39:57+0200"}